unassigner/__init__.py
unassigner/algorithm.py
unassigner/align.py
unassigner/alignment.py
unassigner/ani.py
unassigner/command.py
unassigner/download.py
unassigner/find.py
unassigner/mismatch_db.py
unassigner/parse.py
unassigner/prepare_strain_data.py
unassigner/trim.py
unassigner/unassignment_probability.py
unassigner-1.1.0.dist-info/METADATA
unassigner-1.1.0.dist-info/WHEEL
unassigner-1.1.0.dist-info/entry_points.txt
unassigner-1.1.0.dist-info/top_level.txt
unassigner-1.1.0.dist-info/RECORD
