Metadata-Version: 2.1
Name: unassigner
Version: 1.1.0
Summary: Bacterial species unassigner
Home-page: https://github.com/kylebittinger/unassigner
Author: Kyle Bittinger
Author-email: kylebittinger@gmail.com
License: GPLv2+
Classifier: Intended Audience :: Science/Research
Classifier: License :: OSI Approved :: GNU General Public License v2 or later (GPLv2+)
Classifier: Operating System :: POSIX :: Linux
Classifier: Operating System :: MacOS :: MacOS X
Classifier: Programming Language :: Python :: 3
Classifier: Topic :: Scientific/Engineering :: Bio-Informatics
Requires-Dist: biopython
Requires-Dist: scipy
